LICENSE
README.md
setup.py
pixels2svg/__init__.py
pixels2svg/__main__.py
pixels2svg/__version__.py
pixels2svg/cli.py
pixels2svg/main.py
pixels2svg.egg-info/PKG-INFO
pixels2svg.egg-info/SOURCES.txt
pixels2svg.egg-info/dependency_links.txt
pixels2svg.egg-info/requires.txt
pixels2svg.egg-info/top_level.txt
pixels2svg/utils/__init__.py
pixels2svg/utils/geometry.py
pixels2svg/utils/pixel.py
pixels2svg/utils/preprocessing.py
pixels2svg/utils/svg.py
tests/test_main.py
tests/test_utils_geometry.py
tests/test_utils_pixel.py
tests/test_utils_preprocessing.py
tests/test_utils_svg.py