Metadata-Version: 2.1
Name: pixels2svg
Version: 0.2.3
Summary: pixels2svg : Convert pixels to SVG square-based shapes.
Home-page: https://github.com/ValentinFrancois/pixels2svg
Author: Valentin François
Maintainer: Valentin François
License: GNU General Public License v3 or later (GPLv3+)
Platform: any
Requires-Python: >=3.7.0
License-File: LICENSE
Requires-Dist: connected-components-3d
Requires-Dist: scipy
Requires-Dist: Pillow
Requires-Dist: svgwrite
